notus/scanner/__init__.py
notus/scanner/__version__.py
notus/scanner/cli/__init__.py
notus/scanner/cli/parser.py
notus/scanner/config.py
notus/scanner/daemon.py
notus/scanner/errors.py
notus/scanner/loader/__init__.py
notus/scanner/loader/gpg_sha_verifier.py
notus/scanner/loader/json.py
notus/scanner/loader/loader.py
notus/scanner/messages/__init__.py
notus/scanner/messages/message.py
notus/scanner/messages/result.py
notus/scanner/messages/start.py
notus/scanner/messages/status.py
notus/scanner/messaging/__init__.py
notus/scanner/messaging/mqtt.py
notus/scanner/messaging/publisher.py
notus/scanner/messaging/subscriber.py
notus/scanner/models/__init__.py
notus/scanner/models/packages/__init__.py
notus/scanner/models/packages/deb.py
notus/scanner/models/packages/ebuild.py
notus/scanner/models/packages/package.py
notus/scanner/models/packages/rpm.py
notus/scanner/models/packages/slackware.py
notus/scanner/models/packages/windows.py
notus/scanner/models/vulnerability.py
notus/scanner/scanner.py
notus/scanner/tools/__init__.py
notus/scanner/tools/scanstart.py
notus/scanner/tools/subscriber.py
notus/scanner/utils.py
notus_scanner-22.7.2.dist-info/LICENSE
notus_scanner-22.7.2.dist-info/METADATA
notus_scanner-22.7.2.dist-info/WHEEL
notus_scanner-22.7.2.dist-info/entry_points.txt
notus_scanner-22.7.2.dist-info/RECORD
