Metadata-Version: 2.3
Name: notus-scanner
Version: 22.7.2
Summary: A vulnerability scanner for creating results from local security checks (LSCs) 
License: AGPL-3.0-or-later
Keywords: openvas,Greenbone Vulnerability Management,Vulnerability Scanning,Notus,Open Scanner Protocol,Local Security Checks,LSC
Author: Greenbone AG
Author-email: info@greenbone.net
Requires-Python: >=3.9,<4.0
Classifier: Development Status :: 5 - Production/Stable
Classifier: Intended Audience :: Developers
Classifier: Intended Audience :: System Administrators
Classifier: License :: OSI Approved :: GNU Affero General Public License v3 or later (AGPLv3+)
Classifier: Programming Language :: Python :: 3
Classifier: Programming Language :: Python :: 3.9
Classifier: Programming Language :: Python :: 3.10
Classifier: Programming Language :: Python :: 3.11
Classifier: Programming Language :: Python :: 3.12
Classifier: Programming Language :: Python :: 3.13
Requires-Dist: packaging (<25.1)
Requires-Dist: paho-mqtt (>=1.6,<3.0)
Requires-Dist: psutil (>=7.0,<8.0)
Requires-Dist: python-gnupg (>=0.5.4,<0.6.0)
Requires-Dist: tomli (<3.0.0) ; python_version < "3.11"
Project-URL: Homepage, https://github.com/greenbone/notus-scanner
Project-URL: Repository, https://github.com/greenbone/notus-scanner
